dndm/Blank1.png
dndm/Blank2.png
dndm/Blank3.png
dndm/PlayfairDisplay-Black.ttf
dndm/__init__.py
dndm/cli.py
dndm/datcalc.py
dndm/defi.py
dndm/dnd_sheet_generator.py
dndm-0.2.5.dist-info/licenses/LICENSE
dndm-0.2.5.dist-info/METADATA
dndm-0.2.5.dist-info/WHEEL
dndm-0.2.5.dist-info/entry_points.txt
dndm-0.2.5.dist-info/top_level.txt
dndm-0.2.5.dist-info/RECORD
