Metadata-Version: 2.4
Name: dndm
Version: 0.2.5
Summary: A Dungeons and Dragons CLI tool
Author: Ophelia Van Wye
License: MIT
Requires-Python: <3.14,>=3.9
License-File: LICENSE
Requires-Dist: click
Requires-Dist: term-image
Requires-Dist: Pillow<12,>=9.0
Dynamic: license-file
